presidio_image_redactor/__init__.py
presidio_image_redactor/bbox.py
presidio_image_redactor/dicom_image_pii_verify_engine.py
presidio_image_redactor/dicom_image_redactor_engine.py
presidio_image_redactor/document_intelligence_ocr.py
presidio_image_redactor/entities/__init__.py
presidio_image_redactor/entities/api_request_convertor.py
presidio_image_redactor/entities/image_recognizer_result.py
presidio_image_redactor/entities/invalid_exception.py
presidio_image_redactor/image_analyzer_engine.py
presidio_image_redactor/image_pii_verify_engine.py
presidio_image_redactor/image_processing_engine.py
presidio_image_redactor/image_redactor_engine.py
presidio_image_redactor/ocr.py
presidio_image_redactor/py.typed
presidio_image_redactor/tesseract_ocr.py
presidio_image_redactor-0.0.57.dist-info/METADATA
presidio_image_redactor-0.0.57.dist-info/WHEEL
presidio_image_redactor-0.0.57.dist-info/RECORD
