Metadata-Version: 2.3
Name: presidio-image-redactor
Version: 0.0.57
Summary: Presidio image redactor package
License: MIT
Keywords: presidio_image_redactor
Author: Presidio
Author-email: presidio@microsoft.com
Requires-Python: >=3.9,<3.14
Classifier: License :: OSI Approved :: MIT License
Classifier: Operating System :: OS Independent
Classifier: Programming Language :: Python :: 3.9
Classifier: Programming Language :: Python :: 3.10
Classifier: Programming Language :: Python :: 3.11
Classifier: Programming Language :: Python :: 3.12
Provides-Extra: server
Requires-Dist: azure-ai-formrecognizer (>=3.3.0,<4.0.0)
Requires-Dist: flask (>=1.1) ; extra == "server"
Requires-Dist: gunicorn ; extra == "server"
Requires-Dist: matplotlib (>=3.6)
Requires-Dist: opencv-python (>=4.0.0,<5.0.0)
Requires-Dist: pillow (>=9.0)
Requires-Dist: presidio-analyzer (>=1.9.0)
Requires-Dist: pydicom (>=2.3.0)
Requires-Dist: pypng (>=0.20220715.0)
Requires-Dist: pytesseract (>=0.3.7,<0.4)
Requires-Dist: python-gdcm (>=3.0.24.1)
Requires-Dist: spacy (<3.8.4) ; python_version == "3.9"
Requires-Dist: spacy (>=3.8.7,<4.0.0) ; python_version >= "3.13"
Project-URL: Homepage, https://github.com/Microsoft/presidio
